n0vault/__init__.py
n0vault/__main__.py
n0vault/test/__init__.py
n0vault/test/__main__.py
n0vault/test/test_n0vault.py
n0vault-0.2.12.dist-info/LICENSE
n0vault-0.2.12.dist-info/METADATA
n0vault-0.2.12.dist-info/WHEEL
n0vault-0.2.12.dist-info/top_level.txt
n0vault-0.2.12.dist-info/RECORD
